{
  "id": "2026-07-07-managed-iceberg-materialized-views-are-in-public-preview",
  "title": "Managed Iceberg materialized views are in Public Preview ​",
  "date": "2026-07-07",
  "url": "https://docs.databricks.com/aws/en/release-notes/product/2026/july#managed-iceberg-materialized-views-are-in-public-preview",
  "cloud": "aws",
  "category": "platform",
  "body": "**July 7, 2026**\n\nYou can now create a materialized view that is compatible with external Iceberg readers. This feature is in [Public Preview](/aws/en/release-notes/release-types). To enable it, reach out to your Databricks account team. See [Create a materialized view compatible with external Iceberg readers](/aws/en/iceberg/#materialized-views).",
  "source": "archive",
  "fetched_at": "2026-07-09T10:37:52.425335Z"
}